{
  "top5": [
    {
      "Sembol": "CHTR",
      "Dip_Tarih": "2026-01-28",
      "Dipten_Sonra_%": 13.02,
      "Son_Kapanış": 206.62
    },
    {
      "Sembol": "T",
      "Dip_Tarih": "2026-01-27",
      "Dipten_Sonra_%": 13.46,
      "Son_Kapanış": 26.09
    },
    {
      "Sembol": "TMUS",
      "Dip_Tarih": "2026-01-21",
      "Dipten_Sonra_%": 6.99,
      "Son_Kapanış": 196.44
    },
    {
      "Sembol": "FMS",
      "Dip_Tarih": "2026-01-20",
      "Dipten_Sonra_%": 7.37,
      "Son_Kapanış": 22.67
    },
    {
      "Sembol": "BSX",
      "Dip_Tarih": "2026-01-16",
      "Dipten_Sonra_%": 6.48,
      "Son_Kapanış": 93.78
    }
  ],
  "last_run": "2026-01-30 19:43:32"
}