{
  "top5": [
    {
      "Sembol": "NIO",
      "Dip_Tarih": "2026-02-04",
      "Dipten_Sonra_%": 14.64,
      "Son_Kapanış": 5.09
    },
    {
      "Sembol": "TW",
      "Dip_Tarih": "2026-02-03",
      "Dipten_Sonra_%": 10.91,
      "Son_Kapanış": 110.33
    },
    {
      "Sembol": "ARM",
      "Dip_Tarih": "2026-02-03",
      "Dipten_Sonra_%": 15.59,
      "Son_Kapanış": 120.85
    },
    {
      "Sembol": "EHC",
      "Dip_Tarih": "2026-02-02",
      "Dipten_Sonra_%": 17.66,
      "Son_Kapanış": 110.4
    },
    {
      "Sembol": "WYNN",
      "Dip_Tarih": "2026-01-30",
      "Dipten_Sonra_%": 7.21,
      "Son_Kapanış": 115.19
    }
  ],
  "last_run": "2026-02-06 15:50:48"
}