{
  "top5": [
    {
      "Sembol": "SUZ",
      "Dip_Tarih": "2026-06-10",
      "Dipten_Sonra_%": 4.61,
      "Son_Kapanış": 8.39
    },
    {
      "Sembol": "CEG",
      "Dip_Tarih": "2026-06-10",
      "Dipten_Sonra_%": 13.11,
      "Son_Kapanış": 274.06
    },
    {
      "Sembol": "CPNG",
      "Dip_Tarih": "2026-06-10",
      "Dipten_Sonra_%": 19.05,
      "Son_Kapanış": 18.0
    },
    {
      "Sembol": "EGO",
      "Dip_Tarih": "2026-06-10",
      "Dipten_Sonra_%": 18.29,
      "Son_Kapanış": 33.05
    },
    {
      "Sembol": "WMS",
      "Dip_Tarih": "2026-06-10",
      "Dipten_Sonra_%": 13.61,
      "Son_Kapanış": 147.12
    }
  ],
  "last_run": "2026-06-21 09:04:58"
}